{
	"name": "parentpipe",
	"properties": {
		"activities": [
			{
				"name": "onprem ingestion",
				"type": "ExecutePipeline",
				"dependsOn": [],
				"policy": {
					"secureInput": false
				},
				"userProperties": [],
				"typeProperties": {
					"pipeline": {
						"referenceName": "onprem_ingestion",
						"type": "PipelineReference"
					},
					"waitOnCompletion": true
				}
			},
			{
				"name": "reading data from git",
				"type": "ExecutePipeline",
				"dependsOn": [
					{
						"activity": "onprem ingestion",
						"dependencyConditions": [
							"Succeeded"
						]
					}
				],
				"policy": {
					"secureInput": false
				},
				"userProperties": [],
				"typeProperties": {
					"pipeline": {
						"referenceName": "reading data from git",
						"type": "PipelineReference"
					},
					"waitOnCompletion": true
				}
			},
			{
				"name": "incremental_load",
				"type": "ExecutePipeline",
				"dependsOn": [
					{
						"activity": "reading data from git",
						"dependencyConditions": [
							"Succeeded"
						]
					}
				],
				"policy": {
					"secureInput": false
				},
				"userProperties": [],
				"typeProperties": {
					"pipeline": {
						"referenceName": "API_ingetion_incremental_load",
						"type": "PipelineReference"
					},
					"waitOnCompletion": true
				}
			}
		],
		"annotations": []
	}
}